junit_reporter/__init__.py
junit_reporter/__version__.py
junit_reporter/xml.py
junit_reporter-0.1.0.dist-info/LICENSE
junit_reporter-0.1.0.dist-info/METADATA
junit_reporter-0.1.0.dist-info/WHEEL
junit_reporter-0.1.0.dist-info/top_level.txt
junit_reporter-0.1.0.dist-info/RECORD
